cyclone_cli/__init__.py
cyclone_cli/_version.py
cyclone_cli/cyclone_cli.py
cyclone_cli-0.0.33.dist-info/METADATA
cyclone_cli-0.0.33.dist-info/WHEEL
cyclone_cli-0.0.33.dist-info/entry_points.txt
cyclone_cli-0.0.33.dist-info/top_level.txt
cyclone_cli-0.0.33.dist-info/RECORD
