Metadata-Version: 2.1
Name: cyclone-cli
Version: 0.0.33
Summary: CLI app for Cyclone.
Home-page: https://cyclonecms.com
Author: Pixegami
Author-email: pixegami@gmail.com
License: UNKNOWN
Platform: UNKNOWN
Classifier: Programming Language :: Python :: 3.8
Requires-Dist: requests
